{"v":"5.9.0","fr":25,"ip":0,"op":147,"w":1440,"h":800,"nm":"Hero anamation","ddd":0,"assets":[],"layers":[{"ddd":0,"ind":1,"ty":4,"nm":"Layer 6 Outlines 2","sr":1,"ks":{"o":{"a":0,"k":48,"ix":11},"r":{"a":0,"k":0,"ix":10},"p":{"a":0,"k":[384.06,487.368,0],"ix":2,"l":2},"a":{"a":0,"k":[50.363,315.132,0],"ix":1,"l":2},"s":{"a":0,"k":[100,100,100],"ix":6,"l":2}},"ao":0,"shapes":[{"ty":"gr","it":[{"ind":0,"ty":"sh","ix":1,"ks":{"a":0,"k":{"i":[[0,0],[0,0],[11.215,13.895],[14.432,2.714],[14.416,-2.657]],"o":[[0,0],[0.527,-17.788],[-9.229,-11.443],[-14.433,-2.715],[0,0]],"v":[[47.336,312.632],[47.336,-238.295],[33.559,-288.807],[-4.114,-309.917],[-47.863,-308.76]],"c":false},"ix":2},"nm":"Path 1","mn":"ADBE Vector Shape - Group","hd":false},{"ty":"st","c":{"a":0,"k":[0.388235294118,0.686274509804,0.262745098039,1],"ix":3},"o":{"a":0,"k":100,"ix":4},"w":{"a":0,"k":1,"ix":5},"lc":1,"lj":1,"ml":10,"bm":0,"nm":"Stroke 1","mn":"ADBE Vector Graphic - Stroke","hd":false},{"ty":"tr","p":{"a":0,"k":[50.363,315.132],"ix":2},"a":{"a":0,"k":[0,0],"ix":1},"s":{"a":0,"k":[100,100],"ix":3},"r":{"a":0,"k":0,"ix":6},"o":{"a":0,"k":100,"ix":7},"sk":{"a":0,"k":0,"ix":4},"sa":{"a":0,"k":0,"ix":5},"nm":"Transform"}],"nm":"Group 1","np":2,"cix":2,"bm":0,"ix":1,"mn":"ADBE Vector Group","hd":false},{"ty":"tm","s":{"a":1,"k":[{"i":{"x":[0.3],"y":[1]},"o":{"x":[0.3],"y":[0]},"t":0,"s":[0]},{"t":63,"s":[100]}],"ix":1},"e":{"a":1,"k":[{"i":{"x":[0.3],"y":[1]},"o":{"x":[0.3],"y":[0]},"t":5,"s":[1]},{"t":68,"s":[100]}],"ix":2},"o":{"a":0,"k":0,"ix":3},"m":1,"ix":2,"nm":"Trim Paths 1","mn":"ADBE Vector Filter - Trim","hd":false}],"ip":0,"op":1250,"st":0,"bm":0},{"ddd":0,"ind":2,"ty":4,"nm":"Layer 9 Outlines 2","sr":1,"ks":{"o":{"a":0,"k":48,"ix":11},"r":{"a":0,"k":0,"ix":10},"p":{"a":0,"k":[354.911,178.526,0],"ix":2,"l":2},"a":{"a":0,"k":[62.075,52.328,0],"ix":1,"l":2},"s":{"a":0,"k":[100,100,100],"ix":6,"l":2}},"ao":0,"shapes":[{"ty":"gr","it":[{"ind":0,"ty":"sh","ix":1,"ks":{"a":0,"k":{"i":[[0,0],[7.551,-7.063],[10.246,1.322],[7.748,5.338],[8.576,3.859],[8.628,-3.767],[-8.78,12.261],[-14.493,4.135],[-12.068,-17.634],[5.867,-12.142]],"o":[[0.633,10.314],[-7.551,7.064],[-9.331,-1.201],[-7.748,-5.337],[-8.573,-3.864],[5.395,-14.079],[8.784,-12.258],[20.563,-5.868],[7.46,10.903],[0,0]],"v":[[55.213,12.896],[44.108,40.789],[15.545,50.007],[-9.967,38.598],[-33.717,23.448],[-61.075,21.779],[-41.085,-18.654],[-5.715,-45.461],[50.758,-25.097],[55.208,12.891]],"c":true},"ix":2},"nm":"Path 1","mn":"ADBE Vector Shape - Group","hd":false},{"ty":"st","c":{"a":0,"k":[0.388235294118,0.686274509804,0.262745098039,1],"ix":3},"o":{"a":0,"k":100,"ix":4},"w":{"a":0,"k":1,"ix":5},"lc":2,"lj":2,"bm":0,"nm":"Stroke 1","mn":"ADBE Vector Graphic - Stroke","hd":false},{"ty":"tr","p":{"a":0,"k":[62.075,52.329],"ix":2},"a":{"a":0,"k":[0,0],"ix":1},"s":{"a":0,"k":[100,100],"ix":3},"r":{"a":0,"k":0,"ix":6},"o":{"a":0,"k":100,"ix":7},"sk":{"a":0,"k":0,"ix":4},"sa":{"a":0,"k":0,"ix":5},"nm":"Transform"}],"nm":"Group 1","np":2,"cix":2,"bm":0,"ix":1,"mn":"ADBE Vector Group","hd":false},{"ty":"tm","s":{"a":1,"k":[{"i":{"x":[0.3],"y":[1]},"o":{"x":[0.3],"y":[0]},"t":41,"s":[100]},{"t":82,"s":[0]}],"ix":1},"e":{"a":1,"k":[{"i":{"x":[0.3],"y":[1]},"o":{"x":[0.3],"y":[0]},"t":51,"s":[100]},{"t":95,"s":[0]}],"ix":2},"o":{"a":0,"k":0,"ix":3},"m":1,"ix":2,"nm":"Trim Paths 1","mn":"ADBE Vector Filter - Trim","hd":false}],"ip":0,"op":1250,"st":0,"bm":0},{"ddd":0,"ind":3,"ty":4,"nm":"Layer 8 Outlines 2","sr":1,"ks":{"o":{"a":0,"k":48,"ix":11},"r":{"a":0,"k":0,"ix":10},"p":{"a":0,"k":[143.5,400,0],"ix":2,"l":2},"a":{"a":0,"k":[0.5,400.5,0],"ix":1,"l":2},"s":{"a":0,"k":[100,100,100],"ix":6,"l":2}},"ao":0,"shapes":[{"ty":"gr","it":[{"ind":0,"ty":"sh","ix":1,"ks":{"a":0,"k":{"i":[[0,0],[0,0]],"o":[[0,0],[0,0]],"v":[[0.5,0.5],[0.5,800.5]],"c":false},"ix":2},"nm":"Path 1","mn":"ADBE Vector Shape - Group","hd":false},{"ty":"st","c":{"a":0,"k":[0.388235294118,0.686274509804,0.262745098039,1],"ix":3},"o":{"a":0,"k":100,"ix":4},"w":{"a":0,"k":1,"ix":5},"lc":1,"lj":1,"ml":10,"bm":0,"nm":"Stroke 1","mn":"ADBE Vector Graphic - Stroke","hd":false},{"ty":"tr","p":{"a":0,"k":[0,0],"ix":2},"a":{"a":0,"k":[0,0],"ix":1},"s":{"a":0,"k":[100,100],"ix":3},"r":{"a":0,"k":0,"ix":6},"o":{"a":0,"k":100,"ix":7},"sk":{"a":0,"k":0,"ix":4},"sa":{"a":0,"k":0,"ix":5},"nm":"Transform"}],"nm":"Group 1","np":2,"cix":2,"bm":0,"ix":1,"mn":"ADBE Vector Group","hd":false},{"ty":"tm","s":{"a":1,"k":[{"i":{"x":[0.3],"y":[1]},"o":{"x":[0.3],"y":[0]},"t":0,"s":[100]},{"t":63,"s":[0]}],"ix":1},"e":{"a":1,"k":[{"i":{"x":[0.3],"y":[1]},"o":{"x":[0.3],"y":[0]},"t":5,"s":[100]},{"t":68,"s":[0]}],"ix":2},"o":{"a":0,"k":0,"ix":3},"m":1,"ix":2,"nm":"Trim Paths 1","mn":"ADBE Vector Filter - Trim","hd":false}],"ip":0,"op":1250,"st":0,"bm":0},{"ddd":0,"ind":4,"ty":4,"nm":"Layer 7 Outlines 2","sr":1,"ks":{"o":{"a":0,"k":48,"ix":11},"r":{"a":0,"k":0,"ix":10},"p":{"a":0,"k":[287.5,400,0],"ix":2,"l":2},"a":{"a":0,"k":[0.5,400.5,0],"ix":1,"l":2},"s":{"a":0,"k":[100,100,100],"ix":6,"l":2}},"ao":0,"shapes":[{"ty":"gr","it":[{"ind":0,"ty":"sh","ix":1,"ks":{"a":0,"k":{"i":[[0,0],[0,0]],"o":[[0,0],[0,0]],"v":[[0.5,0.5],[0.5,800.5]],"c":false},"ix":2},"nm":"Path 1","mn":"ADBE Vector Shape - Group","hd":false},{"ty":"st","c":{"a":0,"k":[0.388235294118,0.686274509804,0.262745098039,1],"ix":3},"o":{"a":0,"k":100,"ix":4},"w":{"a":0,"k":1,"ix":5},"lc":1,"lj":1,"ml":10,"bm":0,"nm":"Stroke 1","mn":"ADBE Vector Graphic - Stroke","hd":false},{"ty":"tr","p":{"a":0,"k":[0,0],"ix":2},"a":{"a":0,"k":[0,0],"ix":1},"s":{"a":0,"k":[100,100],"ix":3},"r":{"a":0,"k":0,"ix":6},"o":{"a":0,"k":100,"ix":7},"sk":{"a":0,"k":0,"ix":4},"sa":{"a":0,"k":0,"ix":5},"nm":"Transform"}],"nm":"Group 1","np":2,"cix":2,"bm":0,"ix":1,"mn":"ADBE Vector Group","hd":false},{"ty":"tm","s":{"a":1,"k":[{"i":{"x":[0.3],"y":[1]},"o":{"x":[0.3],"y":[0]},"t":0,"s":[100]},{"t":63,"s":[0]}],"ix":1},"e":{"a":1,"k":[{"i":{"x":[0.3],"y":[1]},"o":{"x":[0.3],"y":[0]},"t":5,"s":[100]},{"t":68,"s":[0]}],"ix":2},"o":{"a":0,"k":0,"ix":3},"m":1,"ix":2,"nm":"Trim Paths 1","mn":"ADBE Vector Filter - Trim","hd":false}],"ip":0,"op":1250,"st":0,"bm":0},{"ddd":0,"ind":5,"ty":4,"nm":"Layer 5 Outlines 2","sr":1,"ks":{"o":{"a":0,"k":48,"ix":11},"r":{"a":0,"k":0,"ix":10},"p":{"a":0,"k":[575.5,400,0],"ix":2,"l":2},"a":{"a":0,"k":[0.5,400.5,0],"ix":1,"l":2},"s":{"a":0,"k":[100,100,100],"ix":6,"l":2}},"ao":0,"shapes":[{"ty":"gr","it":[{"ind":0,"ty":"sh","ix":1,"ks":{"a":0,"k":{"i":[[0,0],[0,0]],"o":[[0,0],[0,0]],"v":[[0.5,0.5],[0.5,800.5]],"c":false},"ix":2},"nm":"Path 1","mn":"ADBE Vector Shape - Group","hd":false},{"ty":"st","c":{"a":0,"k":[0.388235294118,0.686274509804,0.262745098039,1],"ix":3},"o":{"a":0,"k":100,"ix":4},"w":{"a":0,"k":1,"ix":5},"lc":1,"lj":1,"ml":10,"bm":0,"nm":"Stroke 1","mn":"ADBE Vector Graphic - Stroke","hd":false},{"ty":"tr","p":{"a":0,"k":[0,0],"ix":2},"a":{"a":0,"k":[0,0],"ix":1},"s":{"a":0,"k":[100,100],"ix":3},"r":{"a":0,"k":0,"ix":6},"o":{"a":0,"k":100,"ix":7},"sk":{"a":0,"k":0,"ix":4},"sa":{"a":0,"k":0,"ix":5},"nm":"Transform"}],"nm":"Group 1","np":2,"cix":2,"bm":0,"ix":1,"mn":"ADBE Vector Group","hd":false},{"ty":"tm","s":{"a":1,"k":[{"i":{"x":[0.3],"y":[1]},"o":{"x":[0.3],"y":[0]},"t":0,"s":[100]},{"t":63,"s":[0]}],"ix":1},"e":{"a":1,"k":[{"i":{"x":[0.3],"y":[1]},"o":{"x":[0.3],"y":[0]},"t":5,"s":[100]},{"t":68,"s":[0]}],"ix":2},"o":{"a":0,"k":0,"ix":3},"m":1,"ix":2,"nm":"Trim Paths 1","mn":"ADBE Vector Filter - Trim","hd":false}],"ip":0,"op":1250,"st":0,"bm":0},{"ddd":0,"ind":6,"ty":4,"nm":"Layer 4 Outlines 2","sr":1,"ks":{"o":{"a":0,"k":48,"ix":11},"r":{"a":0,"k":0,"ix":10},"p":{"a":0,"k":[720,400,0],"ix":2,"l":2},"a":{"a":0,"k":[0.5,400.5,0],"ix":1,"l":2},"s":{"a":0,"k":[100,100,100],"ix":6,"l":2}},"ao":0,"shapes":[{"ty":"gr","it":[{"ind":0,"ty":"sh","ix":1,"ks":{"a":0,"k":{"i":[[0,0],[0,0]],"o":[[0,0],[0,0]],"v":[[0.5,0.5],[0.5,800.5]],"c":false},"ix":2},"nm":"Path 1","mn":"ADBE Vector Shape - Group","hd":false},{"ty":"st","c":{"a":0,"k":[0.388235294118,0.686274509804,0.262745098039,1],"ix":3},"o":{"a":0,"k":100,"ix":4},"w":{"a":0,"k":1,"ix":5},"lc":1,"lj":1,"ml":10,"bm":0,"nm":"Stroke 1","mn":"ADBE Vector Graphic - Stroke","hd":false},{"ty":"tr","p":{"a":0,"k":[0,0],"ix":2},"a":{"a":0,"k":[0,0],"ix":1},"s":{"a":0,"k":[100,100],"ix":3},"r":{"a":0,"k":0,"ix":6},"o":{"a":0,"k":100,"ix":7},"sk":{"a":0,"k":0,"ix":4},"sa":{"a":0,"k":0,"ix":5},"nm":"Transform"}],"nm":"Group 1","np":2,"cix":2,"bm":0,"ix":1,"mn":"ADBE Vector Group","hd":false},{"ty":"tm","s":{"a":1,"k":[{"i":{"x":[0.3],"y":[1]},"o":{"x":[0.3],"y":[0]},"t":0,"s":[100]},{"t":63,"s":[0]}],"ix":1},"e":{"a":1,"k":[{"i":{"x":[0.3],"y":[1]},"o":{"x":[0.3],"y":[0]},"t":5,"s":[100]},{"t":68,"s":[0]}],"ix":2},"o":{"a":0,"k":0,"ix":3},"m":1,"ix":2,"nm":"Trim Paths 1","mn":"ADBE Vector Filter - Trim","hd":false}],"ip":0,"op":1250,"st":0,"bm":0},{"ddd":0,"ind":7,"ty":4,"nm":"Layer 3 Outlines 2","sr":1,"ks":{"o":{"a":0,"k":48,"ix":11},"r":{"a":0,"k":0,"ix":10},"p":{"a":0,"k":[863.5,400,0],"ix":2,"l":2},"a":{"a":0,"k":[0.5,400.5,0],"ix":1,"l":2},"s":{"a":0,"k":[100,100,100],"ix":6,"l":2}},"ao":0,"shapes":[{"ty":"gr","it":[{"ind":0,"ty":"sh","ix":1,"ks":{"a":0,"k":{"i":[[0,0],[0,0]],"o":[[0,0],[0,0]],"v":[[0.5,0.5],[0.5,800.5]],"c":false},"ix":2},"nm":"Path 1","mn":"ADBE Vector Shape - Group","hd":false},{"ty":"st","c":{"a":0,"k":[0.388235294118,0.686274509804,0.262745098039,1],"ix":3},"o":{"a":0,"k":100,"ix":4},"w":{"a":0,"k":1,"ix":5},"lc":1,"lj":1,"ml":10,"bm":0,"nm":"Stroke 1","mn":"ADBE Vector Graphic - Stroke","hd":false},{"ty":"tr","p":{"a":0,"k":[0,0],"ix":2},"a":{"a":0,"k":[0,0],"ix":1},"s":{"a":0,"k":[100,100],"ix":3},"r":{"a":0,"k":0,"ix":6},"o":{"a":0,"k":100,"ix":7},"sk":{"a":0,"k":0,"ix":4},"sa":{"a":0,"k":0,"ix":5},"nm":"Transform"}],"nm":"Group 1","np":2,"cix":2,"bm":0,"ix":1,"mn":"ADBE Vector Group","hd":false},{"ty":"tm","s":{"a":1,"k":[{"i":{"x":[0.3],"y":[1]},"o":{"x":[0.3],"y":[0]},"t":0,"s":[100]},{"t":63,"s":[0]}],"ix":1},"e":{"a":1,"k":[{"i":{"x":[0.3],"y":[1]},"o":{"x":[0.3],"y":[0]},"t":5,"s":[100]},{"t":68,"s":[0]}],"ix":2},"o":{"a":0,"k":0,"ix":3},"m":1,"ix":2,"nm":"Trim Paths 1","mn":"ADBE Vector Filter - Trim","hd":false}],"ip":0,"op":1250,"st":0,"bm":0},{"ddd":0,"ind":8,"ty":4,"nm":"Layer 2 Outlines 2","sr":1,"ks":{"o":{"a":0,"k":48,"ix":11},"r":{"a":0,"k":0,"ix":10},"p":{"a":0,"k":[1008,400,0],"ix":2,"l":2},"a":{"a":0,"k":[0.5,400.5,0],"ix":1,"l":2},"s":{"a":0,"k":[100,100,100],"ix":6,"l":2}},"ao":0,"shapes":[{"ty":"gr","it":[{"ind":0,"ty":"sh","ix":1,"ks":{"a":0,"k":{"i":[[0,0],[0,0]],"o":[[0,0],[0,0]],"v":[[0.5,0.5],[0.5,800.5]],"c":false},"ix":2},"nm":"Path 1","mn":"ADBE Vector Shape - Group","hd":false},{"ty":"st","c":{"a":0,"k":[0.388235294118,0.686274509804,0.262745098039,1],"ix":3},"o":{"a":0,"k":100,"ix":4},"w":{"a":0,"k":1,"ix":5},"lc":1,"lj":1,"ml":10,"bm":0,"nm":"Stroke 1","mn":"ADBE Vector Graphic - Stroke","hd":false},{"ty":"tr","p":{"a":0,"k":[0,0],"ix":2},"a":{"a":0,"k":[0,0],"ix":1},"s":{"a":0,"k":[100,100],"ix":3},"r":{"a":0,"k":0,"ix":6},"o":{"a":0,"k":100,"ix":7},"sk":{"a":0,"k":0,"ix":4},"sa":{"a":0,"k":0,"ix":5},"nm":"Transform"}],"nm":"Group 1","np":2,"cix":2,"bm":0,"ix":1,"mn":"ADBE Vector Group","hd":false},{"ty":"tm","s":{"a":1,"k":[{"i":{"x":[0.3],"y":[1]},"o":{"x":[0.3],"y":[0]},"t":0,"s":[100]},{"t":63,"s":[0]}],"ix":1},"e":{"a":1,"k":[{"i":{"x":[0.3],"y":[1]},"o":{"x":[0.3],"y":[0]},"t":5,"s":[100]},{"t":68,"s":[0]}],"ix":2},"o":{"a":0,"k":0,"ix":3},"m":1,"ix":2,"nm":"Trim Paths 1","mn":"ADBE Vector Filter - Trim","hd":false}],"ip":0,"op":1250,"st":0,"bm":0},{"ddd":0,"ind":9,"ty":4,"nm":"Layer 10 Outlines 2","sr":1,"ks":{"o":{"a":0,"k":48,"ix":11},"r":{"a":0,"k":0,"ix":10},"p":{"a":0,"k":[1295.5,553.028,0],"ix":2,"l":2},"a":{"a":0,"k":[0.5,247.471,0],"ix":1,"l":2},"s":{"a":0,"k":[100,100,100],"ix":6,"l":2}},"ao":0,"shapes":[{"ty":"gr","it":[{"ind":0,"ty":"sh","ix":1,"ks":{"a":0,"k":{"i":[[0,0],[0,0]],"o":[[0,0],[0,0]],"v":[[0.5,0.5],[0.5,494.443]],"c":false},"ix":2},"nm":"Path 1","mn":"ADBE Vector Shape - Group","hd":false},{"ty":"st","c":{"a":0,"k":[0.388235294118,0.686274509804,0.262745098039,1],"ix":3},"o":{"a":0,"k":100,"ix":4},"w":{"a":0,"k":1,"ix":5},"lc":1,"lj":1,"ml":10,"bm":0,"nm":"Stroke 1","mn":"ADBE Vector Graphic - Stroke","hd":false},{"ty":"tr","p":{"a":0,"k":[0,0],"ix":2},"a":{"a":0,"k":[0,0],"ix":1},"s":{"a":0,"k":[100,100],"ix":3},"r":{"a":0,"k":0,"ix":6},"o":{"a":0,"k":100,"ix":7},"sk":{"a":0,"k":0,"ix":4},"sa":{"a":0,"k":0,"ix":5},"nm":"Transform"}],"nm":"Group 1","np":2,"cix":2,"bm":0,"ix":1,"mn":"ADBE Vector Group","hd":false},{"ty":"tm","s":{"a":1,"k":[{"i":{"x":[0.3],"y":[1]},"o":{"x":[0.3],"y":[0]},"t":0,"s":[100]},{"t":63,"s":[0]}],"ix":1},"e":{"a":1,"k":[{"i":{"x":[0.3],"y":[1]},"o":{"x":[0.3],"y":[0]},"t":5,"s":[100]},{"t":68,"s":[0]}],"ix":2},"o":{"a":0,"k":0,"ix":3},"m":1,"ix":2,"nm":"Trim Paths 1","mn":"ADBE Vector Filter - Trim","hd":false}],"ip":0,"op":1250,"st":0,"bm":0},{"ddd":0,"ind":10,"ty":4,"nm":"Layer 11 Outlines 2","sr":1,"ks":{"o":{"a":0,"k":48,"ix":11},"r":{"a":0,"k":0,"ix":10},"p":{"a":0,"k":[1214.48,524.562,0],"ix":2,"l":2},"a":{"a":0,"k":[65.5,277.939,0],"ix":1,"l":2},"s":{"a":0,"k":[100,100,100],"ix":6,"l":2}},"ao":0,"shapes":[{"ty":"gr","it":[{"ind":0,"ty":"sh","ix":1,"ks":{"a":0,"k":{"i":[[0,0],[15.32,-3.782],[15.39,-11.694],[-0.02,-19.339],[0,0]],"o":[[-15.08,4.548],[-18.75,4.655],[-15.41,11.681],[0,0],[0,0]],"v":[[63,-275.439],[16.98,-264.222],[-35.97,-241.632],[-62.98,-192.656],[-62.98,275.439]],"c":false},"ix":2},"nm":"Path 1","mn":"ADBE Vector Shape - Group","hd":false},{"ty":"st","c":{"a":0,"k":[0.388235294118,0.686274509804,0.262745098039,1],"ix":3},"o":{"a":0,"k":100,"ix":4},"w":{"a":0,"k":1,"ix":5},"lc":1,"lj":1,"ml":10,"bm":0,"nm":"Stroke 1","mn":"ADBE Vector Graphic - Stroke","hd":false},{"ty":"tr","p":{"a":0,"k":[65.5,277.939],"ix":2},"a":{"a":0,"k":[0,0],"ix":1},"s":{"a":0,"k":[100,100],"ix":3},"r":{"a":0,"k":0,"ix":6},"o":{"a":0,"k":100,"ix":7},"sk":{"a":0,"k":0,"ix":4},"sa":{"a":0,"k":0,"ix":5},"nm":"Transform"}],"nm":"Group 1","np":2,"cix":2,"bm":0,"ix":1,"mn":"ADBE Vector Group","hd":false},{"ty":"tm","s":{"a":1,"k":[{"i":{"x":[0.3],"y":[1]},"o":{"x":[0.3],"y":[0]},"t":0,"s":[100]},{"t":63,"s":[0]}],"ix":1},"e":{"a":1,"k":[{"i":{"x":[0.3],"y":[1]},"o":{"x":[0.3],"y":[0]},"t":5,"s":[100]},{"t":68,"s":[0]}],"ix":2},"o":{"a":0,"k":0,"ix":3},"m":1,"ix":2,"nm":"Trim Paths 1","mn":"ADBE Vector Filter - Trim","hd":false}],"ip":0,"op":1250,"st":0,"bm":0},{"ddd":0,"ind":11,"ty":4,"nm":"Layer 15 Outlines 2","sr":1,"ks":{"o":{"a":0,"k":48,"ix":11},"r":{"a":0,"k":0,"ix":10},"p":{"a":0,"k":[1125.955,252.884,0],"ix":2,"l":2},"a":{"a":0,"k":[52.915,48.323,0],"ix":1,"l":2},"s":{"a":0,"k":[100,100,100],"ix":6,"l":2}},"ao":0,"shapes":[{"ty":"gr","it":[{"ind":0,"ty":"sh","ix":1,"ks":{"a":0,"k":{"i":[[0,0],[-3.07,10.848],[6.74,9.025],[10.87,2.951],[11.14,-1.649],[10.78,-3.315],[-1.52,-6.621],[-0.29,-6.788],[-5.86,-9.356],[-11.03,0.593],[-4.39,10.387]],"o":[[11.17,-1.432],[3.06,-10.842],[-6.74,-9.03],[-10.88,-2.951],[-11.14,1.654],[5.97,3.246],[1.52,6.616],[0.47,11.024],[5.85,9.355],[12.21,-0.662],[0,0]],"v":[[23.845,25.275],[48.855,5.649],[42.225,-26.3],[14.395,-44.372],[-19.145,-45.644],[-51.915,-37.44],[-40.865,-21.053],[-39.255,-0.776],[-31.005,30.895],[-3.715,46.73],[23.835,25.28]],"c":true},"ix":2},"nm":"Path 1","mn":"ADBE Vector Shape - Group","hd":false},{"ty":"st","c":{"a":0,"k":[0.388235294118,0.686274509804,0.262745098039,1],"ix":3},"o":{"a":0,"k":100,"ix":4},"w":{"a":0,"k":1,"ix":5},"lc":2,"lj":2,"bm":0,"nm":"Stroke 1","mn":"ADBE Vector Graphic - Stroke","hd":false},{"ty":"tr","p":{"a":0,"k":[52.915,48.323],"ix":2},"a":{"a":0,"k":[0,0],"ix":1},"s":{"a":0,"k":[100,100],"ix":3},"r":{"a":0,"k":0,"ix":6},"o":{"a":0,"k":100,"ix":7},"sk":{"a":0,"k":0,"ix":4},"sa":{"a":0,"k":0,"ix":5},"nm":"Transform"}],"nm":"Group 1","np":2,"cix":2,"bm":0,"ix":1,"mn":"ADBE Vector Group","hd":false},{"ty":"tm","s":{"a":1,"k":[{"i":{"x":[0.3],"y":[1]},"o":{"x":[0.3],"y":[0]},"t":38,"s":[100]},{"t":75,"s":[0]}],"ix":1},"e":{"a":1,"k":[{"i":{"x":[0.3],"y":[1]},"o":{"x":[0.3],"y":[0]},"t":43,"s":[100]},{"t":80,"s":[0]}],"ix":2},"o":{"a":0,"k":0,"ix":3},"m":1,"ix":2,"nm":"Trim Paths 1","mn":"ADBE Vector Filter - Trim","hd":false}],"ip":0,"op":1250,"st":0,"bm":0},{"ddd":0,"ind":12,"ty":4,"nm":"Layer 17 Outlines 2","sr":1,"ks":{"o":{"a":0,"k":48,"ix":11},"r":{"a":0,"k":0,"ix":10},"p":{"a":0,"k":[1215.2,207.521,0],"ix":2,"l":2},"a":{"a":0,"k":[20.48,56.41,0],"ix":1,"l":2},"s":{"a":0,"k":[100,100,100],"ix":6,"l":2}},"ao":0,"shapes":[{"ty":"gr","it":[{"ind":0,"ty":"sh","ix":1,"ks":{"a":0,"k":{"i":[[0,0],[5.92,16.219],[7.14,9.643],[-1.04,11.957]],"o":[[12.26,-12.163],[-4.12,-11.27],[-7.14,-9.642],[0,0]],"v":[[2.88,55.409],[13.56,7.539],[-6.03,-22.479],[-18.44,-55.409]],"c":false},"ix":2},"nm":"Path 1","mn":"ADBE Vector Shape - Group","hd":false},{"ty":"st","c":{"a":0,"k":[0.388235294118,0.686274509804,0.262745098039,1],"ix":3},"o":{"a":0,"k":100,"ix":4},"w":{"a":0,"k":1,"ix":5},"lc":2,"lj":2,"bm":0,"nm":"Stroke 1","mn":"ADBE Vector Graphic - Stroke","hd":false},{"ty":"tr","p":{"a":0,"k":[20.48,56.41],"ix":2},"a":{"a":0,"k":[0,0],"ix":1},"s":{"a":0,"k":[100,100],"ix":3},"r":{"a":0,"k":0,"ix":6},"o":{"a":0,"k":100,"ix":7},"sk":{"a":0,"k":0,"ix":4},"sa":{"a":0,"k":0,"ix":5},"nm":"Transform"}],"nm":"Group 1","np":2,"cix":2,"bm":0,"ix":1,"mn":"ADBE Vector Group","hd":false},{"ty":"tm","s":{"a":1,"k":[{"i":{"x":[0.3],"y":[1]},"o":{"x":[0.3],"y":[0]},"t":39,"s":[0]},{"t":63,"s":[100]}],"ix":1},"e":{"a":1,"k":[{"i":{"x":[0.3],"y":[1]},"o":{"x":[0.3],"y":[0]},"t":44,"s":[0]},{"t":68,"s":[100]}],"ix":2},"o":{"a":0,"k":0,"ix":3},"m":1,"ix":2,"nm":"Trim Paths 1","mn":"ADBE Vector Filter - Trim","hd":false}],"ip":0,"op":1250,"st":0,"bm":0},{"ddd":0,"ind":13,"ty":4,"nm":"Layer 16 Outlines 2","sr":1,"ks":{"o":{"a":0,"k":48,"ix":11},"r":{"a":0,"k":0,"ix":10},"p":{"a":0,"k":[1212.235,176.411,0],"ix":2,"l":2},"a":{"a":0,"k":[54.725,65.667,0],"ix":1,"l":2},"s":{"a":0,"k":[100,100,100],"ix":6,"l":2}},"ao":0,"shapes":[{"ty":"gr","it":[{"ind":0,"ty":"sh","ix":1,"ks":{"a":0,"k":{"i":[[0,0],[-3.5,13.416],[7.63,11.01],[11.28,7.13],[4.79,4.452],[0.88,6.635],[7.05,-10.486],[1.73,-12.38],[-7.19,-11.415],[-12.95,-3.772],[-6.14,1.48],[-2.62,3.878]],"o":[[13.56,-0.27],[3.5,-13.415],[-7.64,-11.009],[-5.53,-3.499],[-4.8,-4.447],[-8.52,9.317],[-7.04,10.487],[-1.91,13.749],[7.19,11.416],[5.93,1.729],[6.13,-1.481],[0,0]],"v":[[20.975,53.889],[50.225,28.473],[42.055,-10.223],[12.215,-36.542],[-3.825,-47.808],[-13.405,-64.668],[-37.535,-35.502],[-51.815,-0.894],[-43.565,38.455],[-12.075,62.202],[6.385,63.187],[20.975,53.895]],"c":true},"ix":2},"nm":"Path 1","mn":"ADBE Vector Shape - Group","hd":false},{"ty":"st","c":{"a":0,"k":[0.388235294118,0.686274509804,0.262745098039,1],"ix":3},"o":{"a":0,"k":100,"ix":4},"w":{"a":0,"k":1,"ix":5},"lc":2,"lj":2,"bm":0,"nm":"Stroke 1","mn":"ADBE Vector Graphic - Stroke","hd":false},{"ty":"tr","p":{"a":0,"k":[54.725,65.668],"ix":2},"a":{"a":0,"k":[0,0],"ix":1},"s":{"a":0,"k":[100,100],"ix":3},"r":{"a":0,"k":0,"ix":6},"o":{"a":0,"k":100,"ix":7},"sk":{"a":0,"k":0,"ix":4},"sa":{"a":0,"k":0,"ix":5},"nm":"Transform"}],"nm":"Group 1","np":2,"cix":2,"bm":0,"ix":1,"mn":"ADBE Vector Group","hd":false},{"ty":"tm","s":{"a":1,"k":[{"i":{"x":[0.3],"y":[1]},"o":{"x":[0.3],"y":[0]},"t":46,"s":[100]},{"t":76,"s":[0]}],"ix":1},"e":{"a":1,"k":[{"i":{"x":[0.3],"y":[1]},"o":{"x":[0.3],"y":[0]},"t":51,"s":[100]},{"t":81,"s":[0]}],"ix":2},"o":{"a":0,"k":0,"ix":3},"m":1,"ix":2,"nm":"Trim Paths 1","mn":"ADBE Vector Filter - Trim","hd":false}],"ip":0,"op":1250,"st":0,"bm":0},{"ddd":0,"ind":14,"ty":4,"nm":"Layer 14 Outlines 2","sr":1,"ks":{"o":{"a":0,"k":48,"ix":11},"r":{"a":0,"k":0,"ix":10},"p":{"a":0,"k":[1135.745,271.715,0],"ix":2,"l":2},"a":{"a":0,"k":[21.555,37.958,0],"ix":1,"l":2},"s":{"a":0,"k":[100,100,100],"ix":6,"l":2}},"ao":0,"shapes":[{"ty":"gr","it":[{"ind":0,"ty":"sh","ix":1,"ks":{"a":0,"k":{"i":[[0,0],[24.29,16.329]],"o":[[-1.07,-29.244],[0,0]],"v":[[20.555,36.958],[-20.555,-36.958]],"c":false},"ix":2},"nm":"Path 1","mn":"ADBE Vector Shape - Group","hd":false},{"ty":"st","c":{"a":0,"k":[0.388235294118,0.686274509804,0.262745098039,1],"ix":3},"o":{"a":0,"k":100,"ix":4},"w":{"a":0,"k":1,"ix":5},"lc":2,"lj":2,"bm":0,"nm":"Stroke 1","mn":"ADBE Vector Graphic - Stroke","hd":false},{"ty":"tr","p":{"a":0,"k":[21.555,37.958],"ix":2},"a":{"a":0,"k":[0,0],"ix":1},"s":{"a":0,"k":[100,100],"ix":3},"r":{"a":0,"k":0,"ix":6},"o":{"a":0,"k":100,"ix":7},"sk":{"a":0,"k":0,"ix":4},"sa":{"a":0,"k":0,"ix":5},"nm":"Transform"}],"nm":"Group 1","np":2,"cix":2,"bm":0,"ix":1,"mn":"ADBE Vector Group","hd":false},{"ty":"tm","s":{"a":1,"k":[{"i":{"x":[0.3],"y":[1]},"o":{"x":[0.3],"y":[0]},"t":30,"s":[0]},{"t":63,"s":[100]}],"ix":1},"e":{"a":1,"k":[{"i":{"x":[0.3],"y":[1]},"o":{"x":[0.3],"y":[0]},"t":35,"s":[0]},{"t":68,"s":[100]}],"ix":2},"o":{"a":0,"k":0,"ix":3},"m":1,"ix":2,"nm":"Trim Paths 1","mn":"ADBE Vector Filter - Trim","hd":false}],"ip":0,"op":1250,"st":0,"bm":0},{"ddd":0,"ind":15,"ty":4,"nm":"Layer 13 Outlines 2","sr":1,"ks":{"o":{"a":0,"k":48,"ix":11},"r":{"a":0,"k":0,"ix":10},"p":{"a":0,"k":[1328.62,265.157,0],"ix":2,"l":2},"a":{"a":0,"k":[53.02,47.712,0],"ix":1,"l":2},"s":{"a":0,"k":[100,100,100],"ix":6,"l":2}},"ao":0,"shapes":[{"ty":"gr","it":[{"ind":0,"ty":"sh","ix":1,"ks":{"a":0,"k":{"i":[[0,0],[-1.21,8.964],[-8.26,3.693],[-9.64,-3.233],[-9.79,-2.738],[-8.11,4.341],[9.83,-14.519],[17.39,-2.29],[8.31,8.493],[-7.84,9.791]],"o":[[-6.98,-5.752],[1.22,-8.963],[9.28,-4.141],[9.63,3.238],[9.78,2.737],[-0.59,17.526],[-9.83,14.523],[-11.78,1.552],[-8.32,-8.493],[0,0]],"v":[[-41.33,2.426],[-50.81,-21.767],[-35.23,-42.571],[-5.47,-42.007],[22.99,-31.145],[52.02,-32.435],[37.14,17.304],[-5.65,45.16],[-38.61,35.362],[-41.32,2.416]],"c":true},"ix":2},"nm":"Path 1","mn":"ADBE Vector Shape - Group","hd":false},{"ty":"st","c":{"a":0,"k":[0.388235294118,0.686274509804,0.262745098039,1],"ix":3},"o":{"a":0,"k":100,"ix":4},"w":{"a":0,"k":1,"ix":5},"lc":2,"lj":2,"bm":0,"nm":"Stroke 1","mn":"ADBE Vector Graphic - Stroke","hd":false},{"ty":"tr","p":{"a":0,"k":[53.02,47.712],"ix":2},"a":{"a":0,"k":[0,0],"ix":1},"s":{"a":0,"k":[100,100],"ix":3},"r":{"a":0,"k":0,"ix":6},"o":{"a":0,"k":100,"ix":7},"sk":{"a":0,"k":0,"ix":4},"sa":{"a":0,"k":0,"ix":5},"nm":"Transform"}],"nm":"Group 1","np":2,"cix":2,"bm":0,"ix":1,"mn":"ADBE Vector Group","hd":false},{"ty":"tm","s":{"a":1,"k":[{"i":{"x":[0.3],"y":[1]},"o":{"x":[0.3],"y":[0]},"t":35,"s":[100]},{"t":98,"s":[0]}],"ix":1},"e":{"a":1,"k":[{"i":{"x":[0.3],"y":[1]},"o":{"x":[0.3],"y":[0]},"t":40,"s":[100]},{"t":103,"s":[0]}],"ix":2},"o":{"a":0,"k":0,"ix":3},"m":1,"ix":2,"nm":"Trim Paths 1","mn":"ADBE Vector Filter - Trim","hd":false}],"ip":0,"op":1250,"st":0,"bm":0},{"ddd":0,"ind":16,"ty":4,"nm":"Layer 19 Outlines 2","sr":1,"ks":{"o":{"a":0,"k":48,"ix":11},"r":{"a":0,"k":0,"ix":10},"p":{"a":0,"k":[1233.875,344.09,0],"ix":2,"l":2},"a":{"a":0,"k":[54.685,57.72,0],"ix":1,"l":2},"s":{"a":0,"k":[100,100,100],"ix":6,"l":2}},"ao":0,"shapes":[{"ty":"gr","it":[{"ind":0,"ty":"sh","ix":1,"ks":{"a":0,"k":{"i":[[0,0],[3.85,9.83],[2.41,10.272],[-5.45,9.838],[-11.13,1.605],[-6.67,-8.921],[-6.69,-2.831],[-3.57,-6.343],[7.31,-14.11],[14.58,-6.306],[17.36,-0.743]],"o":[[4.11,-9.717],[-3.86,-9.825],[-2.57,-10.954],[5.44,-9.843],[11.14,-1.601],[6.26,-3.685],[6.7,2.831],[7.79,13.849],[-7.3,14.109],[-14.58,6.301],[0,0]],"v":[[-37.455,56.72],[-39.425,25.922],[-51.115,-3.45],[-47.105,-36.196],[-20.605,-55.119],[9.235,-43.105],[30.245,-44.009],[45.895,-29.369],[45.495,16.367],[10.515,47.357],[-37.455,56.715]],"c":true},"ix":2},"nm":"Path 1","mn":"ADBE Vector Shape - Group","hd":false},{"ty":"st","c":{"a":0,"k":[0.388235294118,0.686274509804,0.262745098039,1],"ix":3},"o":{"a":0,"k":100,"ix":4},"w":{"a":0,"k":1,"ix":5},"lc":2,"lj":2,"bm":0,"nm":"Stroke 1","mn":"ADBE Vector Graphic - Stroke","hd":false},{"ty":"tr","p":{"a":0,"k":[54.685,57.72],"ix":2},"a":{"a":0,"k":[0,0],"ix":1},"s":{"a":0,"k":[100,100],"ix":3},"r":{"a":0,"k":0,"ix":6},"o":{"a":0,"k":100,"ix":7},"sk":{"a":0,"k":0,"ix":4},"sa":{"a":0,"k":0,"ix":5},"nm":"Transform"}],"nm":"Group 1","np":2,"cix":2,"bm":0,"ix":1,"mn":"ADBE Vector Group","hd":false},{"ty":"tm","s":{"a":1,"k":[{"i":{"x":[0.3],"y":[1]},"o":{"x":[0.3],"y":[0]},"t":37,"s":[0]},{"t":98,"s":[100]}],"ix":1},"e":{"a":1,"k":[{"i":{"x":[0.3],"y":[1]},"o":{"x":[0.3],"y":[0]},"t":42,"s":[0]},{"t":103,"s":[100]}],"ix":2},"o":{"a":0,"k":0,"ix":3},"m":1,"ix":2,"nm":"Trim Paths 1","mn":"ADBE Vector Filter - Trim","hd":false}],"ip":0,"op":1250,"st":0,"bm":0},{"ddd":0,"ind":17,"ty":4,"nm":"Layer 18 Outlines 2","sr":1,"ks":{"o":{"a":0,"k":48,"ix":11},"r":{"a":0,"k":0,"ix":10},"p":{"a":0,"k":[1230.16,309.656,0],"ix":2,"l":2},"a":{"a":0,"k":[14.26,46.227,0],"ix":1,"l":2},"s":{"a":0,"k":[100,100,100],"ix":6,"l":2}},"ao":0,"shapes":[{"ty":"gr","it":[{"ind":0,"ty":"sh","ix":1,"ks":{"a":0,"k":{"i":[[0,0],[-0.85,-17.13],[8.47,-14.91]],"o":[[15.62,7.082],[0.86,17.13],[0,0]],"v":[[-13.26,-45.227],[12.4,-3.586],[-1.52,45.227]],"c":false},"ix":2},"nm":"Path 1","mn":"ADBE Vector Shape - Group","hd":false},{"ty":"st","c":{"a":0,"k":[0.388235294118,0.686274509804,0.262745098039,1],"ix":3},"o":{"a":0,"k":100,"ix":4},"w":{"a":0,"k":1,"ix":5},"lc":2,"lj":2,"bm":0,"nm":"Stroke 1","mn":"ADBE Vector Graphic - Stroke","hd":false},{"ty":"tr","p":{"a":0,"k":[14.26,46.227],"ix":2},"a":{"a":0,"k":[0,0],"ix":1},"s":{"a":0,"k":[100,100],"ix":3},"r":{"a":0,"k":0,"ix":6},"o":{"a":0,"k":100,"ix":7},"sk":{"a":0,"k":0,"ix":4},"sa":{"a":0,"k":0,"ix":5},"nm":"Transform"}],"nm":"Group 1","np":2,"cix":2,"bm":0,"ix":1,"mn":"ADBE Vector Group","hd":false},{"ty":"tm","s":{"a":1,"k":[{"i":{"x":[0.3],"y":[1]},"o":{"x":[0.3],"y":[0]},"t":39,"s":[0]},{"t":68,"s":[100]}],"ix":1},"e":{"a":1,"k":[{"i":{"x":[0.3],"y":[1]},"o":{"x":[0.3],"y":[0]},"t":44,"s":[0]},{"t":73,"s":[100]}],"ix":2},"o":{"a":0,"k":0,"ix":3},"m":1,"ix":2,"nm":"Trim Paths 1","mn":"ADBE Vector Filter - Trim","hd":false}],"ip":0,"op":1250,"st":0,"bm":0},{"ddd":0,"ind":18,"ty":4,"nm":"Layer 12 Outlines 2","sr":1,"ks":{"o":{"a":0,"k":48,"ix":11},"r":{"a":0,"k":0,"ix":10},"p":{"a":0,"k":[1287.835,264.715,0],"ix":2,"l":2},"a":{"a":0,"k":[47.695,9.246,0],"ix":1,"l":2},"s":{"a":0,"k":[100,100,100],"ix":6,"l":2}},"ao":0,"shapes":[{"ty":"gr","it":[{"ind":0,"ty":"sh","ix":1,"ks":{"a":0,"k":{"i":[[0,0],[-10.22,-3.19],[-10.6,-1.497],[-8.75,6.182]],"o":[[10.62,-1.357],[10.22,3.19],[10.61,1.493],[0,0]],"v":[[-46.695,-6.889],[-15.025,-1.827],[15.885,6.754],[46.695,0.895]],"c":false},"ix":2},"nm":"Path 1","mn":"ADBE Vector Shape - Group","hd":false},{"ty":"st","c":{"a":0,"k":[0.388235294118,0.686274509804,0.262745098039,1],"ix":3},"o":{"a":0,"k":100,"ix":4},"w":{"a":0,"k":1,"ix":5},"lc":2,"lj":2,"bm":0,"nm":"Stroke 1","mn":"ADBE Vector Graphic - Stroke","hd":false},{"ty":"tr","p":{"a":0,"k":[47.695,9.247],"ix":2},"a":{"a":0,"k":[0,0],"ix":1},"s":{"a":0,"k":[100,100],"ix":3},"r":{"a":0,"k":0,"ix":6},"o":{"a":0,"k":100,"ix":7},"sk":{"a":0,"k":0,"ix":4},"sa":{"a":0,"k":0,"ix":5},"nm":"Transform"}],"nm":"Group 1","np":2,"cix":2,"bm":0,"ix":1,"mn":"ADBE Vector Group","hd":false},{"ty":"tm","s":{"a":1,"k":[{"i":{"x":[0.3],"y":[1]},"o":{"x":[0.3],"y":[0]},"t":51,"s":[0]},{"t":79,"s":[100]}],"ix":1},"e":{"a":1,"k":[{"i":{"x":[0.3],"y":[1]},"o":{"x":[0.3],"y":[0]},"t":56,"s":[0]},{"t":84,"s":[100]}],"ix":2},"o":{"a":0,"k":0,"ix":3},"m":1,"ix":2,"nm":"Trim Paths 1","mn":"ADBE Vector Filter - Trim","hd":false}],"ip":0,"op":1250,"st":0,"bm":0},{"ddd":0,"ind":19,"ty":4,"nm":"Layer 6 Outlines","sr":1,"ks":{"o":{"a":0,"k":100,"ix":11},"r":{"a":0,"k":0,"ix":10},"p":{"a":0,"k":[384.06,487.368,0],"ix":2,"l":2},"a":{"a":0,"k":[50.363,315.132,0],"ix":1,"l":2},"s":{"a":0,"k":[100,100,100],"ix":6,"l":2}},"ao":0,"shapes":[{"ty":"gr","it":[{"ind":0,"ty":"sh","ix":1,"ks":{"a":0,"k":{"i":[[0,0],[0,0],[11.215,13.895],[14.432,2.714],[14.416,-2.657]],"o":[[0,0],[0.527,-17.788],[-9.229,-11.443],[-14.433,-2.715],[0,0]],"v":[[47.336,312.632],[47.336,-238.295],[33.559,-288.807],[-4.114,-309.917],[-47.863,-308.76]],"c":false},"ix":2},"nm":"Path 1","mn":"ADBE Vector Shape - Group","hd":false},{"ty":"st","c":{"a":0,"k":[0.137254901961,0.20000001496,0.223529426724,1],"ix":3},"o":{"a":0,"k":100,"ix":4},"w":{"a":0,"k":1,"ix":5},"lc":1,"lj":1,"ml":10,"bm":0,"nm":"Stroke 1","mn":"ADBE Vector Graphic - Stroke","hd":false},{"ty":"tr","p":{"a":0,"k":[50.363,315.132],"ix":2},"a":{"a":0,"k":[0,0],"ix":1},"s":{"a":0,"k":[100,100],"ix":3},"r":{"a":0,"k":0,"ix":6},"o":{"a":0,"k":100,"ix":7},"sk":{"a":0,"k":0,"ix":4},"sa":{"a":0,"k":0,"ix":5},"nm":"Transform"}],"nm":"Group 1","np":2,"cix":2,"bm":0,"ix":1,"mn":"ADBE Vector Group","hd":false}],"ip":0,"op":1250,"st":0,"bm":0},{"ddd":0,"ind":20,"ty":4,"nm":"Layer 9 Outlines","sr":1,"ks":{"o":{"a":0,"k":100,"ix":11},"r":{"a":0,"k":0,"ix":10},"p":{"a":0,"k":[354.911,178.526,0],"ix":2,"l":2},"a":{"a":0,"k":[62.075,52.328,0],"ix":1,"l":2},"s":{"a":0,"k":[100,100,100],"ix":6,"l":2}},"ao":0,"shapes":[{"ty":"gr","it":[{"ind":0,"ty":"sh","ix":1,"ks":{"a":0,"k":{"i":[[0,0],[7.551,-7.063],[10.246,1.322],[7.748,5.338],[8.576,3.859],[8.628,-3.767],[-8.78,12.261],[-14.493,4.135],[-12.068,-17.634],[5.867,-12.142]],"o":[[0.633,10.314],[-7.551,7.064],[-9.331,-1.201],[-7.748,-5.337],[-8.573,-3.864],[5.395,-14.079],[8.784,-12.258],[20.563,-5.868],[7.46,10.903],[0,0]],"v":[[55.213,12.896],[44.108,40.789],[15.545,50.007],[-9.967,38.598],[-33.717,23.448],[-61.075,21.779],[-41.085,-18.654],[-5.715,-45.461],[50.758,-25.097],[55.208,12.891]],"c":true},"ix":2},"nm":"Path 1","mn":"ADBE Vector Shape - Group","hd":false},{"ty":"st","c":{"a":0,"k":[0.137254901961,0.20000001496,0.223529426724,1],"ix":3},"o":{"a":0,"k":100,"ix":4},"w":{"a":0,"k":1,"ix":5},"lc":2,"lj":2,"bm":0,"nm":"Stroke 1","mn":"ADBE Vector Graphic - Stroke","hd":false},{"ty":"tr","p":{"a":0,"k":[62.075,52.329],"ix":2},"a":{"a":0,"k":[0,0],"ix":1},"s":{"a":0,"k":[100,100],"ix":3},"r":{"a":0,"k":0,"ix":6},"o":{"a":0,"k":100,"ix":7},"sk":{"a":0,"k":0,"ix":4},"sa":{"a":0,"k":0,"ix":5},"nm":"Transform"}],"nm":"Group 1","np":2,"cix":2,"bm":0,"ix":1,"mn":"ADBE Vector Group","hd":false}],"ip":0,"op":1250,"st":0,"bm":0},{"ddd":0,"ind":21,"ty":4,"nm":"Layer 8 Outlines","sr":1,"ks":{"o":{"a":0,"k":100,"ix":11},"r":{"a":0,"k":0,"ix":10},"p":{"a":0,"k":[143.5,400,0],"ix":2,"l":2},"a":{"a":0,"k":[0.5,400.5,0],"ix":1,"l":2},"s":{"a":0,"k":[100,100,100],"ix":6,"l":2}},"ao":0,"shapes":[{"ty":"gr","it":[{"ind":0,"ty":"sh","ix":1,"ks":{"a":0,"k":{"i":[[0,0],[0,0]],"o":[[0,0],[0,0]],"v":[[0.5,0.5],[0.5,800.5]],"c":false},"ix":2},"nm":"Path 1","mn":"ADBE Vector Shape - Group","hd":false},{"ty":"st","c":{"a":0,"k":[0.137254901961,0.20000001496,0.223529426724,1],"ix":3},"o":{"a":0,"k":100,"ix":4},"w":{"a":0,"k":1,"ix":5},"lc":1,"lj":1,"ml":10,"bm":0,"nm":"Stroke 1","mn":"ADBE Vector Graphic - Stroke","hd":false},{"ty":"tr","p":{"a":0,"k":[0,0],"ix":2},"a":{"a":0,"k":[0,0],"ix":1},"s":{"a":0,"k":[100,100],"ix":3},"r":{"a":0,"k":0,"ix":6},"o":{"a":0,"k":100,"ix":7},"sk":{"a":0,"k":0,"ix":4},"sa":{"a":0,"k":0,"ix":5},"nm":"Transform"}],"nm":"Group 1","np":2,"cix":2,"bm":0,"ix":1,"mn":"ADBE Vector Group","hd":false}],"ip":0,"op":1250,"st":0,"bm":0},{"ddd":0,"ind":22,"ty":4,"nm":"Layer 7 Outlines","sr":1,"ks":{"o":{"a":0,"k":100,"ix":11},"r":{"a":0,"k":0,"ix":10},"p":{"a":0,"k":[287.5,400,0],"ix":2,"l":2},"a":{"a":0,"k":[0.5,400.5,0],"ix":1,"l":2},"s":{"a":0,"k":[100,100,100],"ix":6,"l":2}},"ao":0,"shapes":[{"ty":"gr","it":[{"ind":0,"ty":"sh","ix":1,"ks":{"a":0,"k":{"i":[[0,0],[0,0]],"o":[[0,0],[0,0]],"v":[[0.5,0.5],[0.5,800.5]],"c":false},"ix":2},"nm":"Path 1","mn":"ADBE Vector Shape - Group","hd":false},{"ty":"st","c":{"a":0,"k":[0.137254901961,0.20000001496,0.223529426724,1],"ix":3},"o":{"a":0,"k":100,"ix":4},"w":{"a":0,"k":1,"ix":5},"lc":1,"lj":1,"ml":10,"bm":0,"nm":"Stroke 1","mn":"ADBE Vector Graphic - Stroke","hd":false},{"ty":"tr","p":{"a":0,"k":[0,0],"ix":2},"a":{"a":0,"k":[0,0],"ix":1},"s":{"a":0,"k":[100,100],"ix":3},"r":{"a":0,"k":0,"ix":6},"o":{"a":0,"k":100,"ix":7},"sk":{"a":0,"k":0,"ix":4},"sa":{"a":0,"k":0,"ix":5},"nm":"Transform"}],"nm":"Group 1","np":2,"cix":2,"bm":0,"ix":1,"mn":"ADBE Vector Group","hd":false}],"ip":0,"op":1250,"st":0,"bm":0},{"ddd":0,"ind":23,"ty":4,"nm":"Layer 5 Outlines","sr":1,"ks":{"o":{"a":0,"k":100,"ix":11},"r":{"a":0,"k":0,"ix":10},"p":{"a":0,"k":[575.5,400,0],"ix":2,"l":2},"a":{"a":0,"k":[0.5,400.5,0],"ix":1,"l":2},"s":{"a":0,"k":[100,100,100],"ix":6,"l":2}},"ao":0,"shapes":[{"ty":"gr","it":[{"ind":0,"ty":"sh","ix":1,"ks":{"a":0,"k":{"i":[[0,0],[0,0]],"o":[[0,0],[0,0]],"v":[[0.5,0.5],[0.5,800.5]],"c":false},"ix":2},"nm":"Path 1","mn":"ADBE Vector Shape - Group","hd":false},{"ty":"st","c":{"a":0,"k":[0.137254901961,0.20000001496,0.223529426724,1],"ix":3},"o":{"a":0,"k":100,"ix":4},"w":{"a":0,"k":1,"ix":5},"lc":1,"lj":1,"ml":10,"bm":0,"nm":"Stroke 1","mn":"ADBE Vector Graphic - Stroke","hd":false},{"ty":"tr","p":{"a":0,"k":[0,0],"ix":2},"a":{"a":0,"k":[0,0],"ix":1},"s":{"a":0,"k":[100,100],"ix":3},"r":{"a":0,"k":0,"ix":6},"o":{"a":0,"k":100,"ix":7},"sk":{"a":0,"k":0,"ix":4},"sa":{"a":0,"k":0,"ix":5},"nm":"Transform"}],"nm":"Group 1","np":2,"cix":2,"bm":0,"ix":1,"mn":"ADBE Vector Group","hd":false}],"ip":0,"op":1250,"st":0,"bm":0},{"ddd":0,"ind":24,"ty":4,"nm":"Layer 4 Outlines","sr":1,"ks":{"o":{"a":0,"k":100,"ix":11},"r":{"a":0,"k":0,"ix":10},"p":{"a":0,"k":[720,400,0],"ix":2,"l":2},"a":{"a":0,"k":[0.5,400.5,0],"ix":1,"l":2},"s":{"a":0,"k":[100,100,100],"ix":6,"l":2}},"ao":0,"shapes":[{"ty":"gr","it":[{"ind":0,"ty":"sh","ix":1,"ks":{"a":0,"k":{"i":[[0,0],[0,0]],"o":[[0,0],[0,0]],"v":[[0.5,0.5],[0.5,800.5]],"c":false},"ix":2},"nm":"Path 1","mn":"ADBE Vector Shape - Group","hd":false},{"ty":"st","c":{"a":0,"k":[0.137254901961,0.20000001496,0.223529426724,1],"ix":3},"o":{"a":0,"k":100,"ix":4},"w":{"a":0,"k":1,"ix":5},"lc":1,"lj":1,"ml":10,"bm":0,"nm":"Stroke 1","mn":"ADBE Vector Graphic - Stroke","hd":false},{"ty":"tr","p":{"a":0,"k":[0,0],"ix":2},"a":{"a":0,"k":[0,0],"ix":1},"s":{"a":0,"k":[100,100],"ix":3},"r":{"a":0,"k":0,"ix":6},"o":{"a":0,"k":100,"ix":7},"sk":{"a":0,"k":0,"ix":4},"sa":{"a":0,"k":0,"ix":5},"nm":"Transform"}],"nm":"Group 1","np":2,"cix":2,"bm":0,"ix":1,"mn":"ADBE Vector Group","hd":false}],"ip":0,"op":1250,"st":0,"bm":0},{"ddd":0,"ind":25,"ty":4,"nm":"Layer 3 Outlines","sr":1,"ks":{"o":{"a":0,"k":100,"ix":11},"r":{"a":0,"k":0,"ix":10},"p":{"a":0,"k":[863.5,400,0],"ix":2,"l":2},"a":{"a":0,"k":[0.5,400.5,0],"ix":1,"l":2},"s":{"a":0,"k":[100,100,100],"ix":6,"l":2}},"ao":0,"shapes":[{"ty":"gr","it":[{"ind":0,"ty":"sh","ix":1,"ks":{"a":0,"k":{"i":[[0,0],[0,0]],"o":[[0,0],[0,0]],"v":[[0.5,0.5],[0.5,800.5]],"c":false},"ix":2},"nm":"Path 1","mn":"ADBE Vector Shape - Group","hd":false},{"ty":"st","c":{"a":0,"k":[0.137254901961,0.20000001496,0.223529426724,1],"ix":3},"o":{"a":0,"k":100,"ix":4},"w":{"a":0,"k":1,"ix":5},"lc":1,"lj":1,"ml":10,"bm":0,"nm":"Stroke 1","mn":"ADBE Vector Graphic - Stroke","hd":false},{"ty":"tr","p":{"a":0,"k":[0,0],"ix":2},"a":{"a":0,"k":[0,0],"ix":1},"s":{"a":0,"k":[100,100],"ix":3},"r":{"a":0,"k":0,"ix":6},"o":{"a":0,"k":100,"ix":7},"sk":{"a":0,"k":0,"ix":4},"sa":{"a":0,"k":0,"ix":5},"nm":"Transform"}],"nm":"Group 1","np":2,"cix":2,"bm":0,"ix":1,"mn":"ADBE Vector Group","hd":false}],"ip":0,"op":1250,"st":0,"bm":0},{"ddd":0,"ind":26,"ty":4,"nm":"Layer 2 Outlines","sr":1,"ks":{"o":{"a":0,"k":100,"ix":11},"r":{"a":0,"k":0,"ix":10},"p":{"a":0,"k":[1008,400,0],"ix":2,"l":2},"a":{"a":0,"k":[0.5,400.5,0],"ix":1,"l":2},"s":{"a":0,"k":[100,100,100],"ix":6,"l":2}},"ao":0,"shapes":[{"ty":"gr","it":[{"ind":0,"ty":"sh","ix":1,"ks":{"a":0,"k":{"i":[[0,0],[0,0]],"o":[[0,0],[0,0]],"v":[[0.5,0.5],[0.5,800.5]],"c":false},"ix":2},"nm":"Path 1","mn":"ADBE Vector Shape - Group","hd":false},{"ty":"st","c":{"a":0,"k":[0.137254901961,0.20000001496,0.223529426724,1],"ix":3},"o":{"a":0,"k":100,"ix":4},"w":{"a":0,"k":1,"ix":5},"lc":1,"lj":1,"ml":10,"bm":0,"nm":"Stroke 1","mn":"ADBE Vector Graphic - Stroke","hd":false},{"ty":"tr","p":{"a":0,"k":[0,0],"ix":2},"a":{"a":0,"k":[0,0],"ix":1},"s":{"a":0,"k":[100,100],"ix":3},"r":{"a":0,"k":0,"ix":6},"o":{"a":0,"k":100,"ix":7},"sk":{"a":0,"k":0,"ix":4},"sa":{"a":0,"k":0,"ix":5},"nm":"Transform"}],"nm":"Group 1","np":2,"cix":2,"bm":0,"ix":1,"mn":"ADBE Vector Group","hd":false}],"ip":0,"op":1250,"st":0,"bm":0},{"ddd":0,"ind":27,"ty":4,"nm":"Layer 10 Outlines","sr":1,"ks":{"o":{"a":0,"k":100,"ix":11},"r":{"a":0,"k":0,"ix":10},"p":{"a":0,"k":[1295.5,553.028,0],"ix":2,"l":2},"a":{"a":0,"k":[0.5,247.471,0],"ix":1,"l":2},"s":{"a":0,"k":[100,100,100],"ix":6,"l":2}},"ao":0,"shapes":[{"ty":"gr","it":[{"ind":0,"ty":"sh","ix":1,"ks":{"a":0,"k":{"i":[[0,0],[0,0]],"o":[[0,0],[0,0]],"v":[[0.5,0.5],[0.5,494.443]],"c":false},"ix":2},"nm":"Path 1","mn":"ADBE Vector Shape - Group","hd":false},{"ty":"st","c":{"a":0,"k":[0.137254901961,0.20000001496,0.223529426724,1],"ix":3},"o":{"a":0,"k":100,"ix":4},"w":{"a":0,"k":1,"ix":5},"lc":1,"lj":1,"ml":10,"bm":0,"nm":"Stroke 1","mn":"ADBE Vector Graphic - Stroke","hd":false},{"ty":"tr","p":{"a":0,"k":[0,0],"ix":2},"a":{"a":0,"k":[0,0],"ix":1},"s":{"a":0,"k":[100,100],"ix":3},"r":{"a":0,"k":0,"ix":6},"o":{"a":0,"k":100,"ix":7},"sk":{"a":0,"k":0,"ix":4},"sa":{"a":0,"k":0,"ix":5},"nm":"Transform"}],"nm":"Group 1","np":2,"cix":2,"bm":0,"ix":1,"mn":"ADBE Vector Group","hd":false}],"ip":0,"op":1250,"st":0,"bm":0},{"ddd":0,"ind":28,"ty":4,"nm":"Layer 11 Outlines","sr":1,"ks":{"o":{"a":0,"k":100,"ix":11},"r":{"a":0,"k":0,"ix":10},"p":{"a":0,"k":[1214.48,524.562,0],"ix":2,"l":2},"a":{"a":0,"k":[65.5,277.939,0],"ix":1,"l":2},"s":{"a":0,"k":[100,100,100],"ix":6,"l":2}},"ao":0,"shapes":[{"ty":"gr","it":[{"ind":0,"ty":"sh","ix":1,"ks":{"a":0,"k":{"i":[[0,0],[15.32,-3.782],[15.39,-11.694],[-0.02,-19.339],[0,0]],"o":[[-15.08,4.548],[-18.75,4.655],[-15.41,11.681],[0,0],[0,0]],"v":[[63,-275.439],[16.98,-264.222],[-35.97,-241.632],[-62.98,-192.656],[-62.98,275.439]],"c":false},"ix":2},"nm":"Path 1","mn":"ADBE Vector Shape - Group","hd":false},{"ty":"st","c":{"a":0,"k":[0.137254901961,0.20000001496,0.223529426724,1],"ix":3},"o":{"a":0,"k":100,"ix":4},"w":{"a":0,"k":1,"ix":5},"lc":1,"lj":1,"ml":10,"bm":0,"nm":"Stroke 1","mn":"ADBE Vector Graphic - Stroke","hd":false},{"ty":"tr","p":{"a":0,"k":[65.5,277.939],"ix":2},"a":{"a":0,"k":[0,0],"ix":1},"s":{"a":0,"k":[100,100],"ix":3},"r":{"a":0,"k":0,"ix":6},"o":{"a":0,"k":100,"ix":7},"sk":{"a":0,"k":0,"ix":4},"sa":{"a":0,"k":0,"ix":5},"nm":"Transform"}],"nm":"Group 1","np":2,"cix":2,"bm":0,"ix":1,"mn":"ADBE Vector Group","hd":false}],"ip":0,"op":1250,"st":0,"bm":0},{"ddd":0,"ind":29,"ty":4,"nm":"Layer 15 Outlines","sr":1,"ks":{"o":{"a":0,"k":100,"ix":11},"r":{"a":0,"k":0,"ix":10},"p":{"a":0,"k":[1125.955,252.884,0],"ix":2,"l":2},"a":{"a":0,"k":[52.915,48.323,0],"ix":1,"l":2},"s":{"a":0,"k":[100,100,100],"ix":6,"l":2}},"ao":0,"shapes":[{"ty":"gr","it":[{"ind":0,"ty":"sh","ix":1,"ks":{"a":0,"k":{"i":[[0,0],[-3.07,10.848],[6.74,9.025],[10.87,2.951],[11.14,-1.649],[10.78,-3.315],[-1.52,-6.621],[-0.29,-6.788],[-5.86,-9.356],[-11.03,0.593],[-4.39,10.387]],"o":[[11.17,-1.432],[3.06,-10.842],[-6.74,-9.03],[-10.88,-2.951],[-11.14,1.654],[5.97,3.246],[1.52,6.616],[0.47,11.024],[5.85,9.355],[12.21,-0.662],[0,0]],"v":[[23.845,25.275],[48.855,5.649],[42.225,-26.3],[14.395,-44.372],[-19.145,-45.644],[-51.915,-37.44],[-40.865,-21.053],[-39.255,-0.776],[-31.005,30.895],[-3.715,46.73],[23.835,25.28]],"c":true},"ix":2},"nm":"Path 1","mn":"ADBE Vector Shape - Group","hd":false},{"ty":"st","c":{"a":0,"k":[0.137254901961,0.20000001496,0.223529426724,1],"ix":3},"o":{"a":0,"k":100,"ix":4},"w":{"a":0,"k":1,"ix":5},"lc":2,"lj":2,"bm":0,"nm":"Stroke 1","mn":"ADBE Vector Graphic - Stroke","hd":false},{"ty":"tr","p":{"a":0,"k":[52.915,48.323],"ix":2},"a":{"a":0,"k":[0,0],"ix":1},"s":{"a":0,"k":[100,100],"ix":3},"r":{"a":0,"k":0,"ix":6},"o":{"a":0,"k":100,"ix":7},"sk":{"a":0,"k":0,"ix":4},"sa":{"a":0,"k":0,"ix":5},"nm":"Transform"}],"nm":"Group 1","np":2,"cix":2,"bm":0,"ix":1,"mn":"ADBE Vector Group","hd":false}],"ip":0,"op":1250,"st":0,"bm":0},{"ddd":0,"ind":30,"ty":4,"nm":"Layer 17 Outlines","sr":1,"ks":{"o":{"a":0,"k":100,"ix":11},"r":{"a":0,"k":0,"ix":10},"p":{"a":0,"k":[1215.2,207.521,0],"ix":2,"l":2},"a":{"a":0,"k":[20.48,56.41,0],"ix":1,"l":2},"s":{"a":0,"k":[100,100,100],"ix":6,"l":2}},"ao":0,"shapes":[{"ty":"gr","it":[{"ind":0,"ty":"sh","ix":1,"ks":{"a":0,"k":{"i":[[0,0],[5.92,16.219],[7.14,9.643],[-1.04,11.957]],"o":[[12.26,-12.163],[-4.12,-11.27],[-7.14,-9.642],[0,0]],"v":[[2.88,55.409],[13.56,7.539],[-6.03,-22.479],[-18.44,-55.409]],"c":false},"ix":2},"nm":"Path 1","mn":"ADBE Vector Shape - Group","hd":false},{"ty":"st","c":{"a":0,"k":[0.137254901961,0.20000001496,0.223529426724,1],"ix":3},"o":{"a":0,"k":100,"ix":4},"w":{"a":0,"k":1,"ix":5},"lc":2,"lj":2,"bm":0,"nm":"Stroke 1","mn":"ADBE Vector Graphic - Stroke","hd":false},{"ty":"tr","p":{"a":0,"k":[20.48,56.41],"ix":2},"a":{"a":0,"k":[0,0],"ix":1},"s":{"a":0,"k":[100,100],"ix":3},"r":{"a":0,"k":0,"ix":6},"o":{"a":0,"k":100,"ix":7},"sk":{"a":0,"k":0,"ix":4},"sa":{"a":0,"k":0,"ix":5},"nm":"Transform"}],"nm":"Group 1","np":2,"cix":2,"bm":0,"ix":1,"mn":"ADBE Vector Group","hd":false}],"ip":0,"op":1250,"st":0,"bm":0},{"ddd":0,"ind":31,"ty":4,"nm":"Layer 16 Outlines","sr":1,"ks":{"o":{"a":0,"k":100,"ix":11},"r":{"a":0,"k":0,"ix":10},"p":{"a":0,"k":[1212.235,176.411,0],"ix":2,"l":2},"a":{"a":0,"k":[54.725,65.667,0],"ix":1,"l":2},"s":{"a":0,"k":[100,100,100],"ix":6,"l":2}},"ao":0,"shapes":[{"ty":"gr","it":[{"ind":0,"ty":"sh","ix":1,"ks":{"a":0,"k":{"i":[[0,0],[-3.5,13.416],[7.63,11.01],[11.28,7.13],[4.79,4.452],[0.88,6.635],[7.05,-10.486],[1.73,-12.38],[-7.19,-11.415],[-12.95,-3.772],[-6.14,1.48],[-2.62,3.878]],"o":[[13.56,-0.27],[3.5,-13.415],[-7.64,-11.009],[-5.53,-3.499],[-4.8,-4.447],[-8.52,9.317],[-7.04,10.487],[-1.91,13.749],[7.19,11.416],[5.93,1.729],[6.13,-1.481],[0,0]],"v":[[20.975,53.889],[50.225,28.473],[42.055,-10.223],[12.215,-36.542],[-3.825,-47.808],[-13.405,-64.668],[-37.535,-35.502],[-51.815,-0.894],[-43.565,38.455],[-12.075,62.202],[6.385,63.187],[20.975,53.895]],"c":true},"ix":2},"nm":"Path 1","mn":"ADBE Vector Shape - Group","hd":false},{"ty":"st","c":{"a":0,"k":[0.137254901961,0.20000001496,0.223529426724,1],"ix":3},"o":{"a":0,"k":100,"ix":4},"w":{"a":0,"k":1,"ix":5},"lc":2,"lj":2,"bm":0,"nm":"Stroke 1","mn":"ADBE Vector Graphic - Stroke","hd":false},{"ty":"tr","p":{"a":0,"k":[54.725,65.668],"ix":2},"a":{"a":0,"k":[0,0],"ix":1},"s":{"a":0,"k":[100,100],"ix":3},"r":{"a":0,"k":0,"ix":6},"o":{"a":0,"k":100,"ix":7},"sk":{"a":0,"k":0,"ix":4},"sa":{"a":0,"k":0,"ix":5},"nm":"Transform"}],"nm":"Group 1","np":2,"cix":2,"bm":0,"ix":1,"mn":"ADBE Vector Group","hd":false}],"ip":0,"op":1250,"st":0,"bm":0},{"ddd":0,"ind":32,"ty":4,"nm":"Layer 14 Outlines","sr":1,"ks":{"o":{"a":0,"k":100,"ix":11},"r":{"a":0,"k":0,"ix":10},"p":{"a":0,"k":[1135.745,271.715,0],"ix":2,"l":2},"a":{"a":0,"k":[21.555,37.958,0],"ix":1,"l":2},"s":{"a":0,"k":[100,100,100],"ix":6,"l":2}},"ao":0,"shapes":[{"ty":"gr","it":[{"ind":0,"ty":"sh","ix":1,"ks":{"a":0,"k":{"i":[[0,0],[24.29,16.329]],"o":[[-1.07,-29.244],[0,0]],"v":[[20.555,36.958],[-20.555,-36.958]],"c":false},"ix":2},"nm":"Path 1","mn":"ADBE Vector Shape - Group","hd":false},{"ty":"st","c":{"a":0,"k":[0.137254901961,0.20000001496,0.223529426724,1],"ix":3},"o":{"a":0,"k":100,"ix":4},"w":{"a":0,"k":1,"ix":5},"lc":2,"lj":2,"bm":0,"nm":"Stroke 1","mn":"ADBE Vector Graphic - Stroke","hd":false},{"ty":"tr","p":{"a":0,"k":[21.555,37.958],"ix":2},"a":{"a":0,"k":[0,0],"ix":1},"s":{"a":0,"k":[100,100],"ix":3},"r":{"a":0,"k":0,"ix":6},"o":{"a":0,"k":100,"ix":7},"sk":{"a":0,"k":0,"ix":4},"sa":{"a":0,"k":0,"ix":5},"nm":"Transform"}],"nm":"Group 1","np":2,"cix":2,"bm":0,"ix":1,"mn":"ADBE Vector Group","hd":false}],"ip":0,"op":1250,"st":0,"bm":0},{"ddd":0,"ind":33,"ty":4,"nm":"Layer 13 Outlines","sr":1,"ks":{"o":{"a":0,"k":100,"ix":11},"r":{"a":0,"k":0,"ix":10},"p":{"a":0,"k":[1328.62,265.157,0],"ix":2,"l":2},"a":{"a":0,"k":[53.02,47.712,0],"ix":1,"l":2},"s":{"a":0,"k":[100,100,100],"ix":6,"l":2}},"ao":0,"shapes":[{"ty":"gr","it":[{"ind":0,"ty":"sh","ix":1,"ks":{"a":0,"k":{"i":[[0,0],[-1.21,8.964],[-8.26,3.693],[-9.64,-3.233],[-9.79,-2.738],[-8.11,4.341],[9.83,-14.519],[17.39,-2.29],[8.31,8.493],[-7.84,9.791]],"o":[[-6.98,-5.752],[1.22,-8.963],[9.28,-4.141],[9.63,3.238],[9.78,2.737],[-0.59,17.526],[-9.83,14.523],[-11.78,1.552],[-8.32,-8.493],[0,0]],"v":[[-41.33,2.426],[-50.81,-21.767],[-35.23,-42.571],[-5.47,-42.007],[22.99,-31.145],[52.02,-32.435],[37.14,17.304],[-5.65,45.16],[-38.61,35.362],[-41.32,2.416]],"c":true},"ix":2},"nm":"Path 1","mn":"ADBE Vector Shape - Group","hd":false},{"ty":"st","c":{"a":0,"k":[0.137254901961,0.20000001496,0.223529426724,1],"ix":3},"o":{"a":0,"k":100,"ix":4},"w":{"a":0,"k":1,"ix":5},"lc":2,"lj":2,"bm":0,"nm":"Stroke 1","mn":"ADBE Vector Graphic - Stroke","hd":false},{"ty":"tr","p":{"a":0,"k":[53.02,47.712],"ix":2},"a":{"a":0,"k":[0,0],"ix":1},"s":{"a":0,"k":[100,100],"ix":3},"r":{"a":0,"k":0,"ix":6},"o":{"a":0,"k":100,"ix":7},"sk":{"a":0,"k":0,"ix":4},"sa":{"a":0,"k":0,"ix":5},"nm":"Transform"}],"nm":"Group 1","np":2,"cix":2,"bm":0,"ix":1,"mn":"ADBE Vector Group","hd":false}],"ip":0,"op":1250,"st":0,"bm":0},{"ddd":0,"ind":34,"ty":4,"nm":"Layer 19 Outlines","sr":1,"ks":{"o":{"a":0,"k":100,"ix":11},"r":{"a":0,"k":0,"ix":10},"p":{"a":0,"k":[1233.875,344.09,0],"ix":2,"l":2},"a":{"a":0,"k":[54.685,57.72,0],"ix":1,"l":2},"s":{"a":0,"k":[100,100,100],"ix":6,"l":2}},"ao":0,"shapes":[{"ty":"gr","it":[{"ind":0,"ty":"sh","ix":1,"ks":{"a":0,"k":{"i":[[0,0],[3.85,9.83],[2.41,10.272],[-5.45,9.838],[-11.13,1.605],[-6.67,-8.921],[-6.69,-2.831],[-3.57,-6.343],[7.31,-14.11],[14.58,-6.306],[17.36,-0.743]],"o":[[4.11,-9.717],[-3.86,-9.825],[-2.57,-10.954],[5.44,-9.843],[11.14,-1.601],[6.26,-3.685],[6.7,2.831],[7.79,13.849],[-7.3,14.109],[-14.58,6.301],[0,0]],"v":[[-37.455,56.72],[-39.425,25.922],[-51.115,-3.45],[-47.105,-36.196],[-20.605,-55.119],[9.235,-43.105],[30.245,-44.009],[45.895,-29.369],[45.495,16.367],[10.515,47.357],[-37.455,56.715]],"c":true},"ix":2},"nm":"Path 1","mn":"ADBE Vector Shape - Group","hd":false},{"ty":"st","c":{"a":0,"k":[0.137254901961,0.20000001496,0.223529426724,1],"ix":3},"o":{"a":0,"k":100,"ix":4},"w":{"a":0,"k":1,"ix":5},"lc":2,"lj":2,"bm":0,"nm":"Stroke 1","mn":"ADBE Vector Graphic - Stroke","hd":false},{"ty":"tr","p":{"a":0,"k":[54.685,57.72],"ix":2},"a":{"a":0,"k":[0,0],"ix":1},"s":{"a":0,"k":[100,100],"ix":3},"r":{"a":0,"k":0,"ix":6},"o":{"a":0,"k":100,"ix":7},"sk":{"a":0,"k":0,"ix":4},"sa":{"a":0,"k":0,"ix":5},"nm":"Transform"}],"nm":"Group 1","np":2,"cix":2,"bm":0,"ix":1,"mn":"ADBE Vector Group","hd":false}],"ip":0,"op":1250,"st":0,"bm":0},{"ddd":0,"ind":35,"ty":4,"nm":"Layer 18 Outlines","sr":1,"ks":{"o":{"a":0,"k":100,"ix":11},"r":{"a":0,"k":0,"ix":10},"p":{"a":0,"k":[1230.16,309.656,0],"ix":2,"l":2},"a":{"a":0,"k":[14.26,46.227,0],"ix":1,"l":2},"s":{"a":0,"k":[100,100,100],"ix":6,"l":2}},"ao":0,"shapes":[{"ty":"gr","it":[{"ind":0,"ty":"sh","ix":1,"ks":{"a":0,"k":{"i":[[0,0],[-0.85,-17.13],[8.47,-14.91]],"o":[[15.62,7.082],[0.86,17.13],[0,0]],"v":[[-13.26,-45.227],[12.4,-3.586],[-1.52,45.227]],"c":false},"ix":2},"nm":"Path 1","mn":"ADBE Vector Shape - Group","hd":false},{"ty":"st","c":{"a":0,"k":[0.137254901961,0.20000001496,0.223529426724,1],"ix":3},"o":{"a":0,"k":100,"ix":4},"w":{"a":0,"k":1,"ix":5},"lc":2,"lj":2,"bm":0,"nm":"Stroke 1","mn":"ADBE Vector Graphic - Stroke","hd":false},{"ty":"tr","p":{"a":0,"k":[14.26,46.227],"ix":2},"a":{"a":0,"k":[0,0],"ix":1},"s":{"a":0,"k":[100,100],"ix":3},"r":{"a":0,"k":0,"ix":6},"o":{"a":0,"k":100,"ix":7},"sk":{"a":0,"k":0,"ix":4},"sa":{"a":0,"k":0,"ix":5},"nm":"Transform"}],"nm":"Group 1","np":2,"cix":2,"bm":0,"ix":1,"mn":"ADBE Vector Group","hd":false}],"ip":0,"op":1250,"st":0,"bm":0},{"ddd":0,"ind":36,"ty":4,"nm":"Layer 12 Outlines","sr":1,"ks":{"o":{"a":0,"k":100,"ix":11},"r":{"a":0,"k":0,"ix":10},"p":{"a":0,"k":[1287.835,264.715,0],"ix":2,"l":2},"a":{"a":0,"k":[47.695,9.246,0],"ix":1,"l":2},"s":{"a":0,"k":[100,100,100],"ix":6,"l":2}},"ao":0,"shapes":[{"ty":"gr","it":[{"ind":0,"ty":"sh","ix":1,"ks":{"a":0,"k":{"i":[[0,0],[-10.22,-3.19],[-10.6,-1.497],[-8.75,6.182]],"o":[[10.62,-1.357],[10.22,3.19],[10.61,1.493],[0,0]],"v":[[-46.695,-6.889],[-15.025,-1.827],[15.885,6.754],[46.695,0.895]],"c":false},"ix":2},"nm":"Path 1","mn":"ADBE Vector Shape - Group","hd":false},{"ty":"st","c":{"a":0,"k":[0.137254901961,0.20000001496,0.223529426724,1],"ix":3},"o":{"a":0,"k":100,"ix":4},"w":{"a":0,"k":1,"ix":5},"lc":2,"lj":2,"bm":0,"nm":"Stroke 1","mn":"ADBE Vector Graphic - Stroke","hd":false},{"ty":"tr","p":{"a":0,"k":[47.695,9.247],"ix":2},"a":{"a":0,"k":[0,0],"ix":1},"s":{"a":0,"k":[100,100],"ix":3},"r":{"a":0,"k":0,"ix":6},"o":{"a":0,"k":100,"ix":7},"sk":{"a":0,"k":0,"ix":4},"sa":{"a":0,"k":0,"ix":5},"nm":"Transform"}],"nm":"Group 1","np":2,"cix":2,"bm":0,"ix":1,"mn":"ADBE Vector Group","hd":false}],"ip":0,"op":1250,"st":0,"bm":0}],"markers":[]}